{
  "project_info": {
    "project_number": "435348418450",
    "project_id": "taskify-dc6bf",
    "storage_bucket": "taskify-dc6bf.firebasestorage.app"
  },
  "client": [
    {
      "client_info": {
        "mobilesdk_app_id": "1:435348418450:android:b0733f19d32eede1691b4b",
        "android_client_info": {
          "package_name": "com.example.taskify"
        }
      },
      "oauth_client": [
        {
          "client_id": "435348418450-oiqkmdgvlagfk884vvm61i95u5mjakrk.apps.googleusercontent.com",
          "client_type": 1,
          "android_info": {
            "package_name": "com.example.taskify",
            "certificate_hash": "b976ed25cb7ef3d983d567db633d212a2269d525"
          }
        },
        {
          "client_id": "435348418450-8d3rmimbgkek45ro0gn7kuft5tjnfgck.apps.googleusercontent.com",
          "client_type": 3
        }
      ],
      "api_key": [
        {
          "current_key": "AIzaSyC3zqIFHzd834bu3TiMUaJTFp2sOSLeMGc"
        }
      ],
      "services": {
        "appinvite_service": {
          "other_platform_oauth_client": [
            {
              "client_id": "435348418450-8d3rmimbgkek45ro0gn7kuft5tjnfgck.apps.googleusercontent.com",
              "client_type": 3
            }
          ]
        }
      }
    }
  ],
  "configuration_version": "1"
}